LICENSE.md
typegraph_std/__init__.py
typegraph_std/github/__init__.py
typegraph_std/github/ghes.py
typegraph_std/github/ghes.pyi
typegraph_std/github/github.py
typegraph_std/github/github.pyi
typegraph_std/google/__init__.py
typegraph_std/google/abusiveexperiencereport.py
typegraph_std/google/abusiveexperiencereport.pyi
typegraph_std/google/acceleratedmobilepageurl.py
typegraph_std/google/acceleratedmobilepageurl.pyi
typegraph_std/google/accessapproval.py
typegraph_std/google/accessapproval.pyi
typegraph_std/google/accesscontextmanager.py
typegraph_std/google/accesscontextmanager.pyi
typegraph_std/google/acmedns.py
typegraph_std/google/acmedns.pyi
typegraph_std/google/adexchangebuyer2.py
typegraph_std/google/adexchangebuyer2.pyi
typegraph_std/google/adexperiencereport.py
typegraph_std/google/adexperiencereport.pyi
typegraph_std/google/admin.py
typegraph_std/google/admin.pyi
typegraph_std/google/admob.py
typegraph_std/google/admob.pyi
typegraph_std/google/adsense.py
typegraph_std/google/adsense.pyi
typegraph_std/google/adsensehost.py
typegraph_std/google/adsensehost.pyi
typegraph_std/google/advisorynotifications.py
typegraph_std/google/advisorynotifications.pyi
typegraph_std/google/alertcenter.py
typegraph_std/google/alertcenter.pyi
typegraph_std/google/analytics.py
typegraph_std/google/analytics.pyi
typegraph_std/google/analyticsadmin.py
typegraph_std/google/analyticsadmin.pyi
typegraph_std/google/analyticsdata.py
typegraph_std/google/analyticsdata.pyi
typegraph_std/google/analyticshub.py
typegraph_std/google/analyticshub.pyi
typegraph_std/google/analyticsreporting.py
typegraph_std/google/analyticsreporting.pyi
typegraph_std/google/androiddeviceprovisioning.py
typegraph_std/google/androiddeviceprovisioning.pyi
typegraph_std/google/androidenterprise.py
typegraph_std/google/androidenterprise.pyi
typegraph_std/google/androidmanagement.py
typegraph_std/google/androidmanagement.pyi
typegraph_std/google/androidpublisher.py
typegraph_std/google/androidpublisher.pyi
typegraph_std-0.0.1.dist-info/LICENSE.md
typegraph_std-0.0.1.dist-info/METADATA
typegraph_std-0.0.1.dist-info/WHEEL
typegraph_std-0.0.1.dist-info/RECORD
