Metadata-Version: 2.1
Name: typegraph-std
Version: 0.0.1
Summary: Metatype standard library.
Home-page: https://metatype.dev
License: MPL-2.0
Keywords: metatype,typegraph
Author: Metatype Contributors
Author-email: support@metatype.dev
Requires-Python: >=3.8,<4.0
Classifier: License :: OSI Approved
Classifier: Programming Language :: Python
Classifier: Programming Language :: Python :: 3
Classifier: Programming Language :: Python :: 3.8
Classifier: Programming Language :: Python :: 3.9
Classifier: Programming Language :: Python :: 3.10
Classifier: Programming Language :: Python :: 3.11
Classifier: Topic :: Software Development :: Libraries :: Python Modules
Requires-Dist: typegraph (>=0.1.9,<0.2.0)
Project-URL: Repository, https://github.com/metatypedev/typegraph_std
